virajchoudhary_nlp/__init__.py
virajchoudhary_nlp/corpus_tools.py
virajchoudhary_nlp/features.py
virajchoudhary_nlp/language_models.py
virajchoudhary_nlp/preprocessing.py
virajchoudhary_nlp-0.0.3.dist-info/METADATA
virajchoudhary_nlp-0.0.3.dist-info/WHEEL
virajchoudhary_nlp-0.0.3.dist-info/top_level.txt
virajchoudhary_nlp-0.0.3.dist-info/RECORD
