Metadata-Version: 2.4
Name: virajchoudhary-nlp
Version: 0.0.3
Summary: A personal toolkit for NLP lab coursework.
Author: Viraj Choudhary
Author-email: virajc188@gmail.com
Classifier: Programming Language :: Python :: 3
Classifier: License :: OSI Approved :: MIT License
Classifier: Operating System :: OS Independent
Requires-Python: >=3.6
Requires-Dist: nltk
Requires-Dist: scikit-learn
Requires-Dist: pandas
Requires-Dist: requests
Requires-Dist: beautifulsoup4
Dynamic: author
Dynamic: author-email
Dynamic: classifier
Dynamic: description
Dynamic: description-content-type
Dynamic: requires-dist
Dynamic: requires-python
Dynamic: summary
